nippe/__init__.py
nippe/weather.py
nippe-0.0.3.dist-info/LICENSE
nippe-0.0.3.dist-info/METADATA
nippe-0.0.3.dist-info/WHEEL
nippe-0.0.3.dist-info/top_level.txt
nippe-0.0.3.dist-info/RECORD
