Metadata-Version: 2.1
Name: nippe
Version: 0.0.3
Summary: Nibe Power Performance Enhancer
Requires-Python: >=3.6
License-File: LICENSE
Requires-Dist: setuptools-git-versioning (>=1.13.0)
Requires-Dist: build (>=0.9.0)
Provides-Extra: dev
Requires-Dist: pytest (==6.2.5) ; extra == 'dev'
Requires-Dist: black (==21.9b0) ; extra == 'dev'
Provides-Extra: doc
Requires-Dist: sphinx (==5.2.0) ; extra == 'doc'
Requires-Dist: sphinx-click (==4.4.0) ; extra == 'doc'
Requires-Dist: sphinx-rtd-theme (==1.1.1) ; extra == 'doc'
